grapdb/__init__.py
grapdb/cli.py
grapdb/graph.py
grapdb/parser.py
grapdb/planner.py
grapdb/py.typed
grapdb/target/__init__.py
grapdb/target/diesel_orm.py
grapdb/target/rsrc/graph_orm_base.py
grapdb/target/rsrc/graph_orm_base_v14.py
grapdb/target/rsrc/graph_orm_base_v20.py
grapdb/target/sa_orm.py
test/__init__.py
test/test_basic.py
grapdb-0.27.0.dist-info/entry_points.txt
grapdb-0.27.0.dist-info/WHEEL
grapdb-0.27.0.dist-info/METADATA
grapdb-0.27.0.dist-info/RECORD
