Metadata-Version: 2.1
Name: grapdb
Version: 0.27.0
Summary: Graph data modeling and code generator for Postgres.
License: MIT
Author-email: Ken Elkabany <ken@elkabany.com>
Requires-Python: >=3.10
Requires-Dist: black>=25.1.0
Requires-Dist: code-writer>=1.3.0
Requires-Dist: toml>=0.10.0
